Metadata-Version: 2.1
Name: gotext
Version: 0.9.5
Summary: GoText is a universal text extraction and preprocessing tool for python which supportss wide variety of document formats.
Home-page: https://github.com/VaibhavHaswani/GoText
Author: Vaibhav Haswani
Author-email: vaibhavhaswani@gmail.com
License: UNKNOWN
Download-URL: https://github.com/VaibhavHaswani/GoText/archive/refs/tags/v0.9.tar.gz
Project-URL: Bug Tracker, https://github.com/VaibhavHaswani/GoText/issues
Keywords: text extraction,text preprocessing,document extraction,text utils
Platform: UNKNOWN
Classifier: Programming Language :: Python :: 3
Classifier: License :: OSI Approved :: GNU General Public License v3 or later (GPLv3+)
Classifier: Operating System :: OS Independent
Requires-Python: >=3.6
